{
  "fetchedAt": "2026-04-29T12:32:02.457Z",
  "languages": [
    {
      "name": "Markdown",
      "percent": 43.7,
      "text": "2 hrs 43 mins"
    },
    {
      "name": "TypeScript",
      "percent": 24.8,
      "text": "1 hr 32 mins"
    },
    {
      "name": "JavaScript",
      "percent": 6.9,
      "text": "25 mins"
    },
    {
      "name": "Java",
      "percent": 5.9,
      "text": "22 mins"
    },
    {
      "name": "PHP",
      "percent": 4,
      "text": "14 mins"
    },
    {
      "name": "Git Config",
      "percent": 3.1,
      "text": "11 mins"
    }
  ]
}