{
  "fetchedAt": "2026-02-23T12:12:15.602Z",
  "languages": [
    {
      "name": "TypeScript",
      "percent": 74.1,
      "text": "7 mins"
    },
    {
      "name": "YAML",
      "percent": 20.8,
      "text": "2 mins"
    },
    {
      "name": "JSON",
      "percent": 2,
      "text": "12 secs"
    },
    {
      "name": "Bash",
      "percent": 1.6,
      "text": "10 secs"
    },
    {
      "name": "Text",
      "percent": 0.7,
      "text": "4 secs"
    },
    {
      "name": "INI",
      "percent": 0.5,
      "text": "3 secs"
    }
  ]
}